auto_filters/__init__.py
django_autofilters-0.1.0.dist-info/METADATA
django_autofilters-0.1.0.dist-info/WHEEL
django_autofilters-0.1.0.dist-info/RECORD
