Metadata-Version: 2.3
Name: django-autofilters
Version: 0.1.0
Summary: Enhanced Django Admin filters with autocomplete support and OR condition combinations
License: MIT
Keywords: django,admin,filters,autocomplete
Author: YoungKwang Yang
Author-email: me@youngkwang.dev
Requires-Python: >=3.10
Classifier: Development Status :: 3 - Alpha
Classifier: Framework :: Django
Classifier: Framework :: Django :: 4.2
Classifier: Framework :: Django :: 5.0
Classifier: Framework :: Django :: 5.1
Classifier: Framework :: Django :: 5.2
Classifier: Intended Audience :: Developers
Classifier: License :: OSI Approved :: MIT License
Classifier: Operating System :: OS Independent
Classifier: Programming Language :: Python :: 3
Classifier: Programming Language :: Python :: 3.10
Classifier: Programming Language :: Python :: 3.11
Classifier: Programming Language :: Python :: 3.12
Classifier: Programming Language :: Python :: 3.13
Requires-Dist: django (>=4.2,<5.3)
Project-URL: Documentation, https://github.com/2ykwang/django-autofilters
Project-URL: Homepage, https://github.com/2ykwang/django-autofilters
Project-URL: Repository, https://github.com/2ykwang/django-autofilters
